reboost/__init__.py
reboost/__main__.py
reboost/_version.py
reboost/build_evt.py
reboost/build_glm.py
reboost/build_hit.py
reboost/cli.py
reboost/core.py
reboost/iterator.py
reboost/log_utils.py
reboost/profile.py
reboost/units.py
reboost/utils.py
reboost/daq/__init__.py
reboost/daq/core.py
reboost/daq/utils.py
reboost/hpge/__init__.py
reboost/hpge/psd.py
reboost/hpge/surface.py
reboost/hpge/utils.py
reboost/math/__init__.py
reboost/math/functions.py
reboost/math/stats.py
reboost/optmap/__init__.py
reboost/optmap/__main__.py
reboost/optmap/cli.py
reboost/optmap/convolve.py
reboost/optmap/create.py
reboost/optmap/evt.py
reboost/optmap/mapview.py
reboost/optmap/numba_pdg.py
reboost/optmap/optmap.py
reboost/shape/__init__.py
reboost/shape/cluster.py
reboost/shape/group.py
reboost/shape/reduction.py
reboost/spms/__init__.py
reboost/spms/pe.py
reboost-0.9.1.dist-info/licenses/LICENSE
reboost-0.9.1.dist-info/METADATA
reboost-0.9.1.dist-info/WHEEL
reboost-0.9.1.dist-info/entry_points.txt
reboost-0.9.1.dist-info/top_level.txt
reboost-0.9.1.dist-info/RECORD
