Metadata-Version: 2.4
Name: reboost
Version: 0.9.1
Summary: New LEGEND Monte-Carlo simulation post-processing
Author-email: Manuel Huber <info@manuelhu.de>, Toby Dixon <toby.dixon.23@ucl.ac.uk>, Luigi Pertoldi <gipert@pm.me>
Maintainer: The LEGEND Collaboration
License-Expression: GPL-3.0
Project-URL: Homepage, https://github.com/legend-exp/reboost
Project-URL: Bug Tracker, https://github.com/legend-exp/reboost/issues
Project-URL: Discussions, https://github.com/legend-exp/reboost/discussions
Project-URL: Changelog, https://github.com/legend-exp/reboost/releases
Classifier: Intended Audience :: Developers
Classifier: Intended Audience :: Science/Research
Classifier: Operating System :: MacOS
Classifier: Operating System :: POSIX
Classifier: Operating System :: Unix
Classifier: Programming Language :: Python
Classifier: Programming Language :: Python :: 3
Classifier: Programming Language :: Python :: 3 :: Only
Classifier: Topic :: Scientific/Engineering
Requires-Python: >=3.10
License-File: LICENSE
Requires-Dist: hdf5plugin
Requires-Dist: colorlog
Requires-Dist: numpy
Requires-Dist: scipy
Requires-Dist: numba>=0.60
Requires-Dist: legend-pydataobj>=1.15.1
Requires-Dist: legend-pygeom-optics>=0.15.0
Requires-Dist: legend-pygeom-tools>=0.0.26
Requires-Dist: legend-pygeom-hpges
Requires-Dist: hist
Requires-Dist: dbetto
Requires-Dist: particle
Requires-Dist: pandas
Requires-Dist: matplotlib
Requires-Dist: pygama
Requires-Dist: pyg4ometry
Provides-Extra: all
Requires-Dist: reboost[docs,test]; extra == "all"
Provides-Extra: docs
Requires-Dist: furo; extra == "docs"
Requires-Dist: myst-parser; extra == "docs"
Requires-Dist: sphinx; extra == "docs"
Requires-Dist: sphinx-copybutton; extra == "docs"
Provides-Extra: test
Requires-Dist: pre-commit; extra == "test"
Requires-Dist: pytest>=6.0; extra == "test"
Requires-Dist: pytest-cov; extra == "test"
Requires-Dist: legend-pygeom-hpges; extra == "test"
Requires-Dist: pylegendtestdata>=0.6; extra == "test"
Dynamic: license-file
